{
  "_class": "text",
  "attributedString": {
    "_class": "attributedString",
    "attributes": [
      {
        "_class": "stringAttribute",
        "attributes": {
          "MSAttributedStringColorAttribute": {
            "_class": "color",
            "alpha": 1,
            "blue": 0.8745098039215686,
            "green": 0.4235294117647059,
            "red": 0.007843137254901886
          },
          "MSAttributedStringFontAttribute": {
            "_class": "fontDescriptor",
            "attributes": {
              "name": "Averta-Semibold",
              "size": 16
            }
          },
          "paragraphStyle": {
            "_class": "paragraphStyle",
            "alignment": 2,
            "maximumLineHeight": 24,
            "minimumLineHeight": 24,
            "paragraphSpacing": 8
          },
          "textStyleVerticalAlignmentKey": 0
        },
        "length": 19,
        "location": 0
      },
      {
        "_class": "stringAttribute",
        "attributes": {
          "MSAttributedStringColorAttribute": {
            "_class": "color",
            "alpha": 0.65,
            "blue": 0.1490196078431373,
            "green": 0.1490196078431373,
            "red": 0.1490196078431373
          },
          "MSAttributedStringFontAttribute": {
            "_class": "fontDescriptor",
            "attributes": {
              "name": "Averta-Regular",
              "size": 16
            }
          },
          "paragraphStyle": {
            "_class": "paragraphStyle",
            "alignment": 2,
            "maximumLineHeight": 24,
            "minimumLineHeight": 24,
            "paragraphSpacing": 8
          },
          "textStyleVerticalAlignmentKey": 0
        },
        "length": 15,
        "location": 19
      }
    ],
    "string": "This is a hyperlink if one exists."
  },
  "automaticallyDrawOnUnderlyingPath": false,
  "booleanOperation": -1,
  "clippingMaskMode": 0,
  "do_objectID": "9D5444D2-E7D3-445A-B2E9-A052DC835E09",
  "dontSynchroniseWithSymbol": false,
  "exportOptions": {
    "_class": "exportOptions",
    "do_objectID": "F312C8E8-AE1F-42DD-957D-E1FA8D05F260",
    "exportFormats": [
    ],
    "includedLayerIds": [
    ],
    "layerOptions": 0,
    "shouldTrim": false
  },
  "frame": {
    "_class": "rect",
    "constrainProportions": false,
    "do_objectID": "41FD2486-4290-4F5A-8B05-CCDD53180CEB",
    "height": 24,
    "width": 229,
    "x": 60.5,
    "y": 90
  },
  "glyphBounds": "{{0, 6}, {228, 16}}",
  "hasClippingMask": false,
  "isFixedToViewport": false,
  "isFlippedHorizontal": false,
  "isFlippedVertical": false,
  "isLocked": false,
  "isVisible": true,
  "layerListExpandedType": 0,
  "lineSpacingBehaviour": 2,
  "name": "Body with Link",
  "nameIsFixed": true,
  "resizingConstraint": 39,
  "resizingType": 0,
  "rotation": 0,
  "shouldBreakMaskChain": false,
  "style": {
    "_class": "style",
    "do_objectID": "B88EE2A0-2683-4B14-99F7-601D8F8243CF",
    "endMarkerType": 0,
    "miterLimit": 10,
    "startMarkerType": 0,
    "textStyle": {
      "_class": "textStyle",
      "do_objectID": "A1791B42-F6AE-4F1F-9217-9E01D1B8E452",
      "encodedAttributes": {
        "MSAttributedStringColorAttribute": {
          "_class": "color",
          "alpha": 1,
          "blue": 0.8745098039215686,
          "green": 0.4235294117647059,
          "red": 0.007843137254901886
        },
        "MSAttributedStringFontAttribute": {
          "_class": "fontDescriptor",
          "attributes": {
            "name": "Averta-Semibold",
            "size": 16
          }
        },
        "paragraphStyle": {
          "_class": "paragraphStyle",
          "alignment": 2,
          "maximumLineHeight": 24,
          "minimumLineHeight": 24,
          "paragraphSpacing": 8
        },
        "textStyleVerticalAlignmentKey": 0
      },
      "verticalAlignment": 0
    },
    "windingRule": 1
  },
  "textBehaviour": 0
}