{
  "_class": "text",
  "attributedString": {
    "_class": "attributedString",
    "attributes": [
      {
        "_class": "stringAttribute",
        "attributes": {
          "MSAttributedStringColorAttribute": {
            "_class": "color",
            "alpha": 1,
            "blue": 0.2,
            "green": 0.2,
            "red": 0.2
          },
          "MSAttributedStringFontAttribute": {
            "_class": "fontDescriptor",
            "attributes": {
              "name": "Averta-Regular",
              "size": 10
            }
          },
          "paragraphStyle": {
            "_class": "paragraphStyle",
            "allowsDefaultTighteningForTruncation": 0
          },
          "textStyleVerticalAlignmentKey": 0
        },
        "length": 18,
        "location": 0
      }
    ],
    "string": "105. Hotel Package"
  },
  "automaticallyDrawOnUnderlyingPath": false,
  "booleanOperation": 0,
  "clippingMaskMode": 0,
  "do_objectID": "88CFC751-68D2-420E-80BF-78E73FA17E7F",
  "dontSynchroniseWithSymbol": false,
  "exportOptions": {
    "_class": "exportOptions",
    "do_objectID": "1FE8E4FF-6A92-40A4-BF1F-7FF642C835DB",
    "exportFormats": [
    ],
    "includedLayerIds": [
    ],
    "layerOptions": 0,
    "shouldTrim": false
  },
  "frame": {
    "_class": "rect",
    "constrainProportions": false,
    "do_objectID": "88030546-F639-4114-BCEC-AE28EE85E1C7",
    "height": 13,
    "width": 88,
    "x": 552,
    "y": 337
  },
  "glyphBounds": "{{0, 2}, {87, 11}}",
  "hasClippingMask": false,
  "isFixedToViewport": false,
  "isFlippedHorizontal": false,
  "isFlippedVertical": false,
  "isLocked": false,
  "isVisible": true,
  "layerListExpandedType": 0,
  "lineSpacingBehaviour": 2,
  "name": "105. Hotel Package",
  "nameIsFixed": false,
  "resizingConstraint": 47,
  "resizingType": 0,
  "rotation": 0,
  "shouldBreakMaskChain": false,
  "style": {
    "_class": "style",
    "do_objectID": "1C11A7D3-2E9C-4ACE-B847-E734E5306BB0",
    "endMarkerType": 0,
    "miterLimit": 10,
    "startMarkerType": 0,
    "textStyle": {
      "_class": "textStyle",
      "do_objectID": "979AF44E-889A-48CF-9316-F44BC9605520",
      "encodedAttributes": {
        "MSAttributedStringColorAttribute": {
          "_class": "color",
          "alpha": 1,
          "blue": 0.2,
          "green": 0.2,
          "red": 0.2
        },
        "MSAttributedStringFontAttribute": {
          "_class": "fontDescriptor",
          "attributes": {
            "name": "Averta-Regular",
            "size": 10
          }
        },
        "paragraphStyle": {
          "_class": "paragraphStyle",
          "allowsDefaultTighteningForTruncation": 0
        },
        "textStyleVerticalAlignmentKey": 0
      },
      "verticalAlignment": 0
    },
    "windingRule": 1
  },
  "textBehaviour": 0
}