{
  "_class": "shapePath",
  "booleanOperation": -1,
  "clippingMaskMode": 0,
  "do_objectID": "C9B27F19-E6C6-4C41-BCD3-5C27CEC367E7",
  "edited": true,
  "exportOptions": {
    "_class": "exportOptions",
    "do_objectID": "89B472D2-1CCE-4798-8A5E-C90A74E6E474",
    "exportFormats": [
    ],
    "includedLayerIds": [
    ],
    "layerOptions": 0,
    "shouldTrim": false
  },
  "frame": {
    "_class": "rect",
    "constrainProportions": false,
    "do_objectID": "81D7D9A0-C677-4557-BAD2-8E61374F2D5B",
    "height": 6,
    "width": 3,
    "x": 0.5,
    "y": 1
  },
  "hasClippingMask": false,
  "isClosed": false,
  "isFixedToViewport": false,
  "isFlippedHorizontal": false,
  "isFlippedVertical": false,
  "isLocked": false,
  "isVisible": true,
  "layerListExpandedType": 1,
  "name": "Stroke 949",
  "nameIsFixed": false,
  "pointRadiusBehaviour": 0,
  "points": [
    {
      "_class": "curvePoint",
      "cornerRadius": 0,
      "curveFrom": "{0, 0.88799999999999579}",
      "curveMode": 4,
      "curveTo": "{0, 0.75}",
      "hasCurveFrom": true,
      "hasCurveTo": false,
      "point": "{0, 0.75}"
    },
    {
      "_class": "curvePoint",
      "cornerRadius": 0,
      "curveFrom": "{0.77599999999999147, 1}",
      "curveMode": 2,
      "curveTo": "{0.2240000000000085, 1}",
      "hasCurveFrom": true,
      "hasCurveTo": true,
      "point": "{0.5, 1}"
    },
    {
      "_class": "curvePoint",
      "cornerRadius": 0,
      "curveFrom": "{1, 0.61183333333330359}",
      "curveMode": 2,
      "curveTo": "{1, 0.88799999999999579}",
      "hasCurveFrom": true,
      "hasCurveTo": true,
      "point": "{1, 0.75}"
    },
    {
      "_class": "curvePoint",
      "cornerRadius": 0,
      "curveFrom": "{0.2240000000000085, 0.5}",
      "curveMode": 2,
      "curveTo": "{0.77599999999999147, 0.5}",
      "hasCurveFrom": true,
      "hasCurveTo": true,
      "point": "{0.5, 0.5}"
    },
    {
      "_class": "curvePoint",
      "cornerRadius": 0,
      "curveFrom": "{0, 0.11183333333330363}",
      "curveMode": 2,
      "curveTo": "{0, 0.38799999999999574}",
      "hasCurveFrom": true,
      "hasCurveTo": true,
      "point": "{0, 0.25}"
    },
    {
      "_class": "curvePoint",
      "cornerRadius": 0,
      "curveFrom": "{0.77599999999999147, 0}",
      "curveMode": 2,
      "curveTo": "{0.2240000000000085, 0}",
      "hasCurveFrom": true,
      "hasCurveTo": true,
      "point": "{0.5, 0}"
    },
    {
      "_class": "curvePoint",
      "cornerRadius": 0,
      "curveFrom": "{1, 0.25}",
      "curveMode": 4,
      "curveTo": "{1, 0.11183333333330363}",
      "hasCurveFrom": false,
      "hasCurveTo": true,
      "point": "{1, 0.25}"
    }
  ],
  "resizingConstraint": 63,
  "resizingType": 0,
  "rotation": 0,
  "shouldBreakMaskChain": false,
  "style": {
    "_class": "style",
    "borderOptions": {
      "_class": "borderOptions",
      "dashPattern": [
      ],
      "do_objectID": "F1EFC239-D4DC-4C22-B4DC-EDC5C8CF8BFF",
      "isEnabled": false,
      "lineCapStyle": 1,
      "lineJoinStyle": 1
    },
    "borders": [
      {
        "_class": "border",
        "color": {
          "_class": "color",
          "alpha": 1,
          "blue": 0.6,
          "green": 0.6,
          "red": 0.6
        },
        "fillType": 0,
        "isEnabled": true,
        "position": 0,
        "thickness": 1
      }
    ],
    "do_objectID": "9CDBD49F-F009-4296-A8CC-1BF467E81BA0",
    "endMarkerType": 0,
    "miterLimit": 10,
    "startMarkerType": 0,
    "windingRule": 1
  }
}