{
  "_class": "rectangle",
  "booleanOperation": 0,
  "clippingMaskMode": 0,
  "do_objectID": "6BD0B602-A2E6-49F7-A892-FA53237E11CE",
  "edited": false,
  "exportOptions": {
    "_class": "exportOptions",
    "do_objectID": "92B042BF-6D64-4FDD-8C48-742A17FFFDB2",
    "exportFormats": [
    ],
    "includedLayerIds": [
    ],
    "layerOptions": 0,
    "shouldTrim": false
  },
  "fixedRadius": 0,
  "frame": {
    "_class": "rect",
    "constrainProportions": true,
    "do_objectID": "3BC812C7-864B-48DD-BC32-88AF722121AE",
    "height": 8.000000000000135,
    "width": 8.00000000000012,
    "x": 31,
    "y": 15.65685424949239
  },
  "hasClippingMask": false,
  "hasConvertedToNewRoundCorners": true,
  "isClosed": true,
  "isFixedToViewport": false,
  "isFlippedHorizontal": false,
  "isFlippedVertical": false,
  "isLocked": false,
  "isVisible": true,
  "layerListExpandedType": 0,
  "name": "Rectangle",
  "nameIsFixed": false,
  "pointRadiusBehaviour": 1,
  "points": [
    {
      "_class": "curvePoint",
      "cornerRadius": 0,
      "curveFrom": "{1.3322676295501878e-14, 1.5987211554602254e-14}",
      "curveMode": 1,
      "curveTo": "{1.3322676295501878e-14, 1.5987211554602254e-14}",
      "hasCurveFrom": false,
      "hasCurveTo": false,
      "point": "{1.3322676295501878e-14, 1.5987211554602254e-14}"
    },
    {
      "_class": "curvePoint",
      "cornerRadius": 0,
      "curveFrom": "{1, 5.3290705182007514e-15}",
      "curveMode": 1,
      "curveTo": "{1, 5.3290705182007514e-15}",
      "hasCurveFrom": false,
      "hasCurveTo": false,
      "point": "{1, 5.3290705182007514e-15}"
    },
    {
      "_class": "curvePoint",
      "cornerRadius": 0,
      "curveFrom": "{1.0000000000000044, 1}",
      "curveMode": 1,
      "curveTo": "{1.0000000000000044, 1}",
      "hasCurveFrom": false,
      "hasCurveTo": false,
      "point": "{1, 0.99999999999999201}"
    },
    {
      "_class": "curvePoint",
      "cornerRadius": 0,
      "curveFrom": "{0, 1.0000000000000053}",
      "curveMode": 1,
      "curveTo": "{0, 1.0000000000000053}",
      "hasCurveFrom": false,
      "hasCurveTo": false,
      "point": "{0, 1.0000000000000053}"
    }
  ],
  "resizingConstraint": 60,
  "resizingType": 0,
  "rotation": -45,
  "shouldBreakMaskChain": false,
  "style": {
    "_class": "style",
    "borders": [
      {
        "_class": "border",
        "color": {
          "_class": "color",
          "alpha": 1,
          "blue": 0.592,
          "green": 0.592,
          "red": 0.592
        },
        "fillType": 0,
        "isEnabled": false,
        "position": 1,
        "thickness": 1
      }
    ],
    "do_objectID": "21A47649-1067-4C3F-A556-558B3ECF0C62",
    "endMarkerType": 0,
    "fills": [
      {
        "_class": "fill",
        "color": {
          "_class": "color",
          "alpha": 1,
          "blue": 0.1764705882352941,
          "green": 0.1490196078431373,
          "red": 0.1215686274509804
        },
        "fillType": 0,
        "isEnabled": true,
        "noiseIndex": 0,
        "noiseIntensity": 0,
        "patternFillType": 1,
        "patternTileScale": 1
      }
    ],
    "miterLimit": 10,
    "shadows": [
      {
        "_class": "shadow",
        "blurRadius": 4,
        "color": {
          "_class": "color",
          "alpha": 0.12,
          "blue": 0,
          "green": 0,
          "red": 0
        },
        "contextSettings": {
          "_class": "graphicsContextSettings",
          "blendMode": 0,
          "opacity": 1
        },
        "isEnabled": false,
        "offsetX": 0,
        "offsetY": 4,
        "spread": 0
      }
    ],
    "startMarkerType": 0,
    "windingRule": 0
  }
}