{
  "_class": "shapePath",
  "booleanOperation": -1,
  "clippingMaskMode": 0,
  "do_objectID": "C471F846-36A4-4183-92F7-FF0E055C78BF",
  "edited": true,
  "exportOptions": {
    "_class": "exportOptions",
    "do_objectID": "0DB7BAB1-C29D-4CA2-AC03-CB528C27E20E",
    "exportFormats": [
    ],
    "includedLayerIds": [
    ],
    "layerOptions": 0,
    "shouldTrim": false
  },
  "frame": {
    "_class": "rect",
    "constrainProportions": false,
    "do_objectID": "6F4589BD-E1F4-42A6-A0F8-2E67431F7DDA",
    "height": 1,
    "width": 7.000000000000242,
    "x": 22.99999999999953,
    "y": 19.99999999999996
  },
  "hasClippingMask": false,
  "isClosed": true,
  "isFixedToViewport": false,
  "isFlippedHorizontal": false,
  "isFlippedVertical": false,
  "isLocked": false,
  "isVisible": true,
  "layerListExpandedType": 0,
  "name": "Path",
  "nameIsFixed": false,
  "pointRadiusBehaviour": 1,
  "points": [
    {
      "_class": "curvePoint",
      "cornerRadius": 0,
      "curveFrom": "{0.9680203392736294, 0}",
      "curveMode": 4,
      "curveTo": "{0.92857142857143105, 0}",
      "hasCurveFrom": true,
      "hasCurveTo": false,
      "point": "{0.92857142857143105, 0}"
    },
    {
      "_class": "curvePoint",
      "cornerRadius": 0,
      "curveFrom": "{1, 0.77614237491539484}",
      "curveMode": 2,
      "curveTo": "{1, 0.22385762508459806}",
      "hasCurveFrom": true,
      "hasCurveTo": true,
      "point": "{1, 0.5}"
    },
    {
      "_class": "curvePoint",
      "cornerRadius": 0,
      "curveFrom": "{0.92857142857143105, 1}",
      "curveMode": 4,
      "curveTo": "{0.9680203392736294, 1}",
      "hasCurveFrom": false,
      "hasCurveTo": true,
      "point": "{0.92857142857143105, 1}"
    },
    {
      "_class": "curvePoint",
      "cornerRadius": 0,
      "curveFrom": "{0.031979660726370554, 1}",
      "curveMode": 4,
      "curveTo": "{0.071428571428568968, 1}",
      "hasCurveFrom": true,
      "hasCurveTo": false,
      "point": "{0.071428571428568968, 1}"
    },
    {
      "_class": "curvePoint",
      "cornerRadius": 0,
      "curveFrom": "{0, 0.22385762508459806}",
      "curveMode": 2,
      "curveTo": "{0, 0.77614237491539484}",
      "hasCurveFrom": true,
      "hasCurveTo": true,
      "point": "{0, 0.5}"
    },
    {
      "_class": "curvePoint",
      "cornerRadius": 0,
      "curveFrom": "{0.071428571428568968, 0}",
      "curveMode": 4,
      "curveTo": "{0.031979660726370554, 0}",
      "hasCurveFrom": false,
      "hasCurveTo": true,
      "point": "{0.071428571428568968, 0}"
    }
  ],
  "resizingConstraint": 63,
  "resizingType": 0,
  "rotation": 0,
  "shouldBreakMaskChain": false,
  "style": {
    "_class": "style",
    "do_objectID": "7BE19738-EB68-4AF8-8E04-BDA23643AA4D",
    "endMarkerType": 0,
    "fills": [
      {
        "_class": "fill",
        "color": {
          "_class": "color",
          "alpha": 1,
          "blue": 0.6,
          "green": 0.6,
          "red": 0.6
        },
        "fillType": 0,
        "isEnabled": true,
        "noiseIndex": 0,
        "noiseIntensity": 0,
        "patternFillType": 1,
        "patternTileScale": 1
      }
    ],
    "miterLimit": 10,
    "startMarkerType": 0,
    "windingRule": 0
  }
}