{
  "_class": "shapePath",
  "booleanOperation": -1,
  "clippingMaskMode": 0,
  "do_objectID": "6B25F55F-7183-492F-A8E2-66987A06112F",
  "edited": true,
  "exportOptions": {
    "_class": "exportOptions",
    "exportFormats": [
    ],
    "includedLayerIds": [
    ],
    "layerOptions": 0,
    "shouldTrim": false
  },
  "frame": {
    "_class": "rect",
    "constrainProportions": false,
    "height": 19,
    "width": 23,
    "x": 0.5000000000001358,
    "y": 2.500000000000037
  },
  "hasClippingMask": false,
  "isClosed": true,
  "isFixedToViewport": false,
  "isFlippedHorizontal": false,
  "isFlippedVertical": false,
  "isLocked": false,
  "isVisible": true,
  "layerListExpandedType": 0,
  "name": "Stroke 7181",
  "nameIsFixed": false,
  "pointRadiusBehaviour": 0,
  "points": [
    {
      "_class": "curvePoint",
      "cornerRadius": 0,
      "curveFrom": "{0.15217391304347827, 0.57894736842105265}",
      "curveMode": 4,
      "curveTo": "{0.56521739130434767, 0.60526315789473095}",
      "hasCurveFrom": true,
      "hasCurveTo": true,
      "point": "{0.56521739130434767, 0.57894736842105254}"
    },
    {
      "_class": "curvePoint",
      "cornerRadius": 0,
      "curveFrom": "{0.17417981315653869, 0.78915075249472122}",
      "curveMode": 1,
      "curveTo": "{0, 1}",
      "hasCurveFrom": false,
      "hasCurveTo": false,
      "point": "{0, 1}"
    },
    {
      "_class": "curvePoint",
      "cornerRadius": 0,
      "curveFrom": "{0.56521739130435134, 0.15789473684210523}",
      "curveMode": 4,
      "curveTo": "{0.021739130434782608, 0.26315789473684209}",
      "hasCurveFrom": true,
      "hasCurveTo": true,
      "point": "{0.56521739130434767, 0.26315789473684204}"
    },
    {
      "_class": "curvePoint",
      "cornerRadius": 0,
      "curveFrom": "{0.56521739130434767, 0}",
      "curveMode": 1,
      "curveTo": "{0.56521739130434767, 0}",
      "hasCurveFrom": false,
      "hasCurveTo": false,
      "point": "{0.56521739130434767, 0}"
    },
    {
      "_class": "curvePoint",
      "cornerRadius": 0,
      "curveFrom": "{1, 0.39473684210526311}",
      "curveMode": 1,
      "curveTo": "{1, 0.39473684210526311}",
      "hasCurveFrom": false,
      "hasCurveTo": false,
      "point": "{1, 0.39473684210526311}"
    },
    {
      "_class": "curvePoint",
      "cornerRadius": 0,
      "curveFrom": "{0.56521739130434767, 0.84210526315789469}",
      "curveMode": 1,
      "curveTo": "{0.56521739130434767, 0.84210526315789469}",
      "hasCurveFrom": false,
      "hasCurveTo": false,
      "point": "{0.56521739130434767, 0.84210526315789469}"
    }
  ],
  "resizingConstraint": 63,
  "resizingType": 0,
  "rotation": 0,
  "sharedStyleID": "905AF934-4C0B-4A31-93DD-6640EACADF15",
  "shouldBreakMaskChain": false,
  "style": {
    "_class": "style",
    "borderOptions": {
      "_class": "borderOptions",
      "dashPattern": [
      ],
      "isEnabled": false,
      "lineCapStyle": 1,
      "lineJoinStyle": 1
    },
    "borders": [
      {
        "_class": "border",
        "color": {
          "_class": "color",
          "alpha": 0.65,
          "blue": 0.1490196078431373,
          "green": 0.1490196078431373,
          "red": 0.1490196078431373
        },
        "fillType": 0,
        "isEnabled": true,
        "position": 0,
        "thickness": 1
      }
    ],
    "do_objectID": "3FB9906F-1338-41B0-9ABA-596D707F2425",
    "endMarkerType": 0,
    "miterLimit": 10,
    "startMarkerType": 0,
    "windingRule": 1
  }
}