{
  "_class": "shapePath",
  "booleanOperation": -1,
  "clippingMaskMode": 0,
  "do_objectID": "C0586EC3-0105-4B3C-B8D4-790BB0B31EC0",
  "edited": true,
  "exportOptions": {
    "_class": "exportOptions",
    "do_objectID": "8AC85062-D340-4F6E-8E64-D16167D51301",
    "exportFormats": [
    ],
    "includedLayerIds": [
    ],
    "layerOptions": 0,
    "shouldTrim": false
  },
  "frame": {
    "_class": "rect",
    "constrainProportions": false,
    "do_objectID": "E2E91227-EBF7-49B7-A5FC-67BAB262819D",
    "height": 2,
    "width": 4,
    "x": 8.5,
    "y": 18.5
  },
  "hasClippingMask": false,
  "isClosed": false,
  "isFixedToViewport": false,
  "isFlippedHorizontal": false,
  "isFlippedVertical": false,
  "isLocked": false,
  "isVisible": true,
  "layerListExpandedType": 0,
  "name": "Line",
  "nameIsFixed": false,
  "pointRadiusBehaviour": 1,
  "points": [
    {
      "_class": "curvePoint",
      "cornerRadius": 0,
      "curveFrom": "{0.12500000000000011, 0.75000000000000011}",
      "curveMode": 1,
      "curveTo": "{0.12500000000000011, 0.75000000000000011}",
      "hasCurveFrom": false,
      "hasCurveTo": false,
      "point": "{0, 0.5}"
    },
    {
      "_class": "curvePoint",
      "cornerRadius": 0,
      "curveFrom": "{-2.1249999999999987, 1.2500000000000002}",
      "curveMode": 1,
      "curveTo": "{-2.1249999999999987, 1.2500000000000002}",
      "hasCurveFrom": false,
      "hasCurveTo": false,
      "point": "{1, 0.5}"
    }
  ],
  "resizingConstraint": 63,
  "resizingType": 0,
  "rotation": 0,
  "shouldBreakMaskChain": false,
  "style": {
    "_class": "style",
    "borderOptions": {
      "_class": "borderOptions",
      "dashPattern": [
      ],
      "do_objectID": "B073496F-D2DB-4BCE-BDE6-59042EA159B3",
      "isEnabled": false,
      "lineCapStyle": 1,
      "lineJoinStyle": 0
    },
    "borders": [
      {
        "_class": "border",
        "color": {
          "_class": "color",
          "alpha": 1,
          "blue": 0.6,
          "green": 0.6,
          "red": 0.6
        },
        "fillType": 0,
        "isEnabled": true,
        "position": 0,
        "thickness": 1
      }
    ],
    "do_objectID": "F782045D-C2B6-46DF-8870-73E7CC5D591B",
    "endMarkerType": 0,
    "fills": [
      {
        "_class": "fill",
        "color": {
          "_class": "color",
          "alpha": 1,
          "blue": 0.847,
          "green": 0.847,
          "red": 0.847
        },
        "fillType": 0,
        "isEnabled": false,
        "noiseIndex": 0,
        "noiseIntensity": 0,
        "patternFillType": 1,
        "patternTileScale": 1
      }
    ],
    "miterLimit": 10,
    "startMarkerType": 0,
    "windingRule": 1
  }
}