{
  "_class": "shapePath",
  "booleanOperation": -1,
  "clippingMaskMode": 0,
  "do_objectID": "4098EA80-5051-4B4B-B784-FA3948D0801F",
  "edited": true,
  "exportOptions": {
    "_class": "exportOptions",
    "do_objectID": "C6D55532-7320-4476-825C-BC96E4C34FB5",
    "exportFormats": [
    ],
    "includedLayerIds": [
    ],
    "layerOptions": 0,
    "shouldTrim": false
  },
  "frame": {
    "_class": "rect",
    "constrainProportions": false,
    "do_objectID": "A6BABD86-C8AE-4CC9-81A6-8A2DD6FAA82A",
    "height": 15,
    "width": 16,
    "x": 4,
    "y": 4
  },
  "hasClippingMask": false,
  "isClosed": true,
  "isFixedToViewport": false,
  "isFlippedHorizontal": false,
  "isFlippedVertical": false,
  "isLocked": false,
  "isVisible": true,
  "layerListExpandedType": 1,
  "name": "Fill 1",
  "nameIsFixed": false,
  "pointRadiusBehaviour": 1,
  "points": [
    {
      "_class": "curvePoint",
      "cornerRadius": 0,
      "curveFrom": "{1, 0}",
      "curveMode": 1,
      "curveTo": "{1, 0}",
      "hasCurveFrom": false,
      "hasCurveTo": false,
      "point": "{1, 0}"
    },
    {
      "_class": "curvePoint",
      "cornerRadius": 0,
      "curveFrom": "{0, 0}",
      "curveMode": 1,
      "curveTo": "{0, 0}",
      "hasCurveFrom": false,
      "hasCurveTo": false,
      "point": "{0, 0}"
    },
    {
      "_class": "curvePoint",
      "cornerRadius": 0,
      "curveFrom": "{0, 0.381963326446281}",
      "curveMode": 1,
      "curveTo": "{0, 0.381963326446281}",
      "hasCurveFrom": false,
      "hasCurveTo": false,
      "point": "{0, 0.381963326446281}"
    },
    {
      "_class": "curvePoint",
      "cornerRadius": 0,
      "curveFrom": "{0, 0.48456146694214869}",
      "curveMode": 1,
      "curveTo": "{0, 0.48456146694214869}",
      "hasCurveFrom": false,
      "hasCurveTo": false,
      "point": "{0, 0.48456146694214869}"
    },
    {
      "_class": "curvePoint",
      "cornerRadius": 0,
      "curveFrom": "{0, 0.99999999999999989}",
      "curveMode": 1,
      "curveTo": "{0, 0.99999999999999989}",
      "hasCurveFrom": false,
      "hasCurveTo": false,
      "point": "{0, 0.99999999999999989}"
    },
    {
      "_class": "curvePoint",
      "cornerRadius": 0,
      "curveFrom": "{0.99999999999999978, 0.99999999999999967}",
      "curveMode": 1,
      "curveTo": "{0.99999999999999978, 0.99999999999999967}",
      "hasCurveFrom": false,
      "hasCurveTo": false,
      "point": "{0.99999999999999978, 0.99999999999999967}"
    },
    {
      "_class": "curvePoint",
      "cornerRadius": 0,
      "curveFrom": "{0.99850907735524863, 0.71474018595041311}",
      "curveMode": 4,
      "curveTo": "{1, 0.7138104338842971}",
      "hasCurveFrom": true,
      "hasCurveTo": false,
      "point": "{1, 0.7138104338842971}"
    }
  ],
  "resizingConstraint": 63,
  "resizingType": 0,
  "rotation": 0,
  "shouldBreakMaskChain": false,
  "style": {
    "_class": "style",
    "do_objectID": "F3667725-543E-4803-8059-D82E9A6124DB",
    "endMarkerType": 0,
    "fills": [
      {
        "_class": "fill",
        "color": {
          "_class": "color",
          "alpha": 1,
          "blue": 0.812,
          "green": 0.435,
          "red": 0
        },
        "fillType": 0,
        "isEnabled": true,
        "noiseIndex": 0,
        "noiseIntensity": 0,
        "patternFillType": 1,
        "patternTileScale": 1
      }
    ],
    "miterLimit": 10,
    "startMarkerType": 0,
    "windingRule": 1
  }
}