{
  "_class": "shapePath",
  "booleanOperation": -1,
  "clippingMaskMode": 0,
  "do_objectID": "9A389BD6-6B23-44E7-96C5-43579D833095",
  "edited": true,
  "exportOptions": {
    "_class": "exportOptions",
    "exportFormats": [
    ],
    "includedLayerIds": [
    ],
    "layerOptions": 0,
    "shouldTrim": false
  },
  "frame": {
    "_class": "rect",
    "constrainProportions": false,
    "height": 4.97,
    "width": 3.682,
    "x": 15.68,
    "y": 0
  },
  "hasClippingMask": false,
  "isClosed": true,
  "isFixedToViewport": false,
  "isFlippedHorizontal": false,
  "isFlippedVertical": false,
  "isLocked": false,
  "isVisible": true,
  "layerListExpandedType": 0,
  "name": "Path",
  "nameIsFixed": false,
  "pointRadiusBehaviour": 1,
  "points": [
    {
      "_class": "curvePoint",
      "cornerRadius": 0,
      "curveFrom": "{0.38212927756654036, 1}",
      "curveMode": 1,
      "curveTo": "{0.38212927756654036, 1}",
      "hasCurveFrom": false,
      "hasCurveTo": false,
      "point": "{0.38212927756654036, 1}"
    },
    {
      "_class": "curvePoint",
      "cornerRadius": 0,
      "curveFrom": "{0.38212927756654036, 0.15211267605633791}",
      "curveMode": 1,
      "curveTo": "{0.38212927756654036, 0.15211267605633791}",
      "hasCurveFrom": false,
      "hasCurveTo": false,
      "point": "{0.38212927756654036, 0.15211267605633791}"
    },
    {
      "_class": "curvePoint",
      "cornerRadius": 0,
      "curveFrom": "{0, 0.15211267605633791}",
      "curveMode": 1,
      "curveTo": "{0, 0.15211267605633791}",
      "hasCurveFrom": false,
      "hasCurveTo": false,
      "point": "{0, 0.15211267605633791}"
    },
    {
      "_class": "curvePoint",
      "cornerRadius": 0,
      "curveFrom": "{0, 0}",
      "curveMode": 1,
      "curveTo": "{0, 0}",
      "hasCurveFrom": false,
      "hasCurveTo": false,
      "point": "{0, 0}"
    },
    {
      "_class": "curvePoint",
      "cornerRadius": 0,
      "curveFrom": "{1, 0}",
      "curveMode": 1,
      "curveTo": "{1, 0}",
      "hasCurveFrom": false,
      "hasCurveTo": false,
      "point": "{1, 0}"
    },
    {
      "_class": "curvePoint",
      "cornerRadius": 0,
      "curveFrom": "{1, 0.15211267605633791}",
      "curveMode": 1,
      "curveTo": "{1, 0.15211267605633791}",
      "hasCurveFrom": false,
      "hasCurveTo": false,
      "point": "{1, 0.15211267605633791}"
    },
    {
      "_class": "curvePoint",
      "cornerRadius": 0,
      "curveFrom": "{0.61216730038022893, 0.15211267605633791}",
      "curveMode": 1,
      "curveTo": "{0.61216730038022893, 0.15211267605633791}",
      "hasCurveFrom": false,
      "hasCurveTo": false,
      "point": "{0.61216730038022893, 0.15211267605633791}"
    },
    {
      "_class": "curvePoint",
      "cornerRadius": 0,
      "curveFrom": "{0.61216730038022893, 1}",
      "curveMode": 1,
      "curveTo": "{0.61216730038022893, 1}",
      "hasCurveFrom": false,
      "hasCurveTo": false,
      "point": "{0.61216730038022893, 1}"
    }
  ],
  "resizingConstraint": 63,
  "resizingType": 0,
  "rotation": 0,
  "shouldBreakMaskChain": false,
  "style": {
    "_class": "style",
    "endMarkerType": 0,
    "miterLimit": 10,
    "startMarkerType": 0,
    "windingRule": 1
  }
}